{
  "credit": "Made with Blockbench",
  "parent": "builtin/entity",
  "texture_size": [
    128,
    128
  ],
  "display": {
    "thirdperson_righthand": {
      "translation": [
        0,
        -5.25,
        -9.25
      ]
    },
    "thirdperson_lefthand": {
      "translation": [
        0,
        -5.25,
        -9.25
      ]
    },
    "firstperson_righthand": {
      "translation": [
        0,
        -2.25,
        -5.75
      ]
    },
    "firstperson_lefthand": {
      "translation": [
        0,
        -2.25,
        -5.75
      ]
    },
    "ground": {
      "translation": [
        0,
        -4,
        0
      ]
    },
    "gui": {
      "rotation": [
        30,
        -135,
        0
      ],
      "translation": [
        7.25,
        -16.25,
        0
      ],
      "scale": [
        1.65,
        1.65,
        1.65
      ]
    },
    "fixed": {
      "rotation": [
        0,
        -90,
        0
      ],
      "translation": [
        6,
        -8,
        0
      ]
    },
    "on_shelf": {
      "rotation": [
        0,
        90,
        0
      ],
      "translation": [
        -4.75,
        -0.5,
        -1.75
      ]
    }
  }
}